igoogle/__init__.py
igoogle/auth.py
igoogle/drive.py
igoogle/gmail.py
igoogle/jupyter.py
igoogle/tests/__init__.py
igoogle/tests/auth.py
igoogle/tests/drive.py
tests/__init__.py
tests/auth.py
tests/dbg.py
tests/drive.py
igoogle-0.0.4.dist-info/LICENSE
igoogle-0.0.4.dist-info/METADATA
igoogle-0.0.4.dist-info/WHEEL
igoogle-0.0.4.dist-info/top_level.txt
igoogle-0.0.4.dist-info/RECORD
