Metadata-Version: 2.1
Name: igoogle
Version: 0.0.4
Summary: innovata-google
Home-page: https://github.com/innovata/igoogle
Author: innovata sambong
Author-email: iinnovata@gmail.com
License: UNKNOWN
Platform: UNKNOWN
Classifier: Programming Language :: Python :: 3
Classifier: License :: OSI Approved :: MIT License
Classifier: Operating System :: OS Independent
